montiege/__init__.py
montiege-0.2.0.dist-info/LICENSE
montiege-0.2.0.dist-info/METADATA
montiege-0.2.0.dist-info/WHEEL
montiege-0.2.0.dist-info/top_level.txt
montiege-0.2.0.dist-info/RECORD
