Metadata-Version: 2.1
Name: montiege
Version: 0.2.0
Summary: Usefull librairy to plot graph
Home-page: https://github.com/HugoooM
Author: Hugo Montiege
Author-email: HugoooM <hugo.montiege@gmail.com>
Project-URL: Homepage, https://github.com/HugoooM
Classifier: Programming Language :: Python :: 3
Classifier: License :: OSI Approved :: MIT License
Classifier: Operating System :: OS Independent
Requires-Python: >=3.8
License-File: LICENSE
